nbedr/__init__.py
nbedr/cli/__init__.py
nbedr/cli/main.py
nbedr/core/__init__.py
nbedr/core/config.py
nbedr/core/models.py
nbedr/core/clients/__init__.py
nbedr/core/clients/aws_bedrock_embedding_provider.py
nbedr/core/clients/azure_openai_embedding_provider.py
nbedr/core/clients/base_embedding_provider.py
nbedr/core/clients/embedding_provider_factory.py
nbedr/core/clients/google_vertex_embedding_provider.py
nbedr/core/clients/llamacpp_embedding_provider.py
nbedr/core/clients/lmstudio_embedding_provider.py
nbedr/core/clients/ollama_embedding_provider.py
nbedr/core/clients/openai_client.py
nbedr/core/clients/openai_embedding_provider.py
nbedr/core/services/__init__.py
nbedr/core/services/document_service.py
nbedr/core/sources/__init__.py
nbedr/core/sources/base.py
nbedr/core/sources/factory.py
nbedr/core/sources/local.py
nbedr/core/sources/s3.py
nbedr/core/sources/sharepoint.py
nbedr/core/utils/__init__.py
nbedr/core/utils/document_coordinator.py
nbedr/core/utils/embedding_utils.py
nbedr/core/utils/env_config.py
nbedr/core/utils/file_utils.py
nbedr/core/utils/identity_utils.py
nbedr/core/utils/instance_coordinator.py
nbedr/core/utils/rate_limiter.py
nbedr/core/vector_stores/__init__.py
nbedr/core/vector_stores/azure_search_store.py
nbedr/core/vector_stores/base.py
nbedr/core/vector_stores/elasticsearch_store.py
nbedr/core/vector_stores/faiss_store.py
nbedr/core/vector_stores/pgvector_store.py
nbedr-1.4.1.dist-info/licenses/LICENSE
nbedr-1.4.1.dist-info/METADATA
nbedr-1.4.1.dist-info/WHEEL
nbedr-1.4.1.dist-info/entry_points.txt
nbedr-1.4.1.dist-info/top_level.txt
nbedr-1.4.1.dist-info/RECORD
