Metadata-Version: 2.4
Name: nbedr
Version: 1.4.1
Summary: nBedR - RAG Embedding Toolkit - Tools for creating and managing embedding databases for Retrieval Augmented Generation
Author: RAG Embeddings Team
License-Expression: GPL-3.0-or-later
Project-URL: Homepage, https://visland.com
Project-URL: Bug Reports, https://github.com/makercorn/nbedr/issues
Project-URL: Source, https://github.com/makercorn/nbedr
Classifier: Development Status :: 4 - Beta
Classifier: Intended Audience :: Developers
Classifier: Programming Language :: Python :: 3
Classifier: Programming Language :: Python :: 3.11
Classifier: Programming Language :: Python :: 3.12
Classifier: Programming Language :: Python :: 3.13
Requires-Python: >=3.11
License-File: LICENSE
Requires-Dist: openai<2.0.0,>=1.0.0
Requires-Dist: python-dotenv<2.0.0,>=1.0.0
Requires-Dist: pydantic<3.0.0,>=2.0.0
Requires-Dist: tqdm<5.0.0,>=4.65.0
Requires-Dist: pandas<3.0.0,>=2.0.0
Requires-Dist: pyarrow<15.0.0,>=14.0.1
Requires-Dist: tiktoken<1.0.0,>=0.5.1
Requires-Dist: pdfplumber<1.0.0,>=0.10.0
Requires-Dist: python-pptx<1.0.0,>=0.6.22
Requires-Dist: langchain-text-splitters<1.0.0,>=0.0.1
Requires-Dist: sentence-transformers<4.0.0,>=3.1.0
Requires-Dist: langchain-openai<1.0.0,>=0.0.2
Requires-Dist: scikit-learn<2.0.0,>=1.3.0
Requires-Dist: numpy<2.0.0,>=1.24.0
Requires-Dist: faiss-cpu<2.0.0,>=1.7.4
Requires-Dist: chromadb<1.0.0,>=0.4.15
Requires-Dist: pinecone-client<4.0.0,>=3.0.0
Provides-Extra: cloud
Requires-Dist: boto3<2.0.0,>=1.34.0; extra == "cloud"
Requires-Dist: botocore<2.0.0,>=1.34.0; extra == "cloud"
Requires-Dist: requests<3.0.0,>=2.31.0; extra == "cloud"
Requires-Dist: requests-oauthlib<2.0.0,>=1.3.0; extra == "cloud"
Requires-Dist: msal<2.0.0,>=1.24.0; extra == "cloud"
Requires-Dist: azure-identity<2.0.0,>=1.15.0; extra == "cloud"
Requires-Dist: azure-storage-blob<13.0.0,>=12.19.0; extra == "cloud"
Provides-Extra: local
Requires-Dist: aiohttp<4.0.0,>=3.8.0; extra == "local"
Provides-Extra: dev
Requires-Dist: pytest>=7.0.0; extra == "dev"
Requires-Dist: pytest-cov>=4.0.0; extra == "dev"
Requires-Dist: pytest-mock>=3.10.0; extra == "dev"
Requires-Dist: pytest-asyncio>=0.21.0; extra == "dev"
Requires-Dist: httpx>=0.24.0; extra == "dev"
Requires-Dist: black>=23.0.0; extra == "dev"
Requires-Dist: isort>=5.12.0; extra == "dev"
Requires-Dist: mypy>=1.0.0; extra == "dev"
Requires-Dist: flake8>=6.0.0; extra == "dev"
Requires-Dist: bandit>=1.7.0; extra == "dev"
Requires-Dist: types-requests>=2.31.0; extra == "dev"
Provides-Extra: all
Requires-Dist: boto3<2.0.0,>=1.34.0; extra == "all"
Requires-Dist: botocore<2.0.0,>=1.34.0; extra == "all"
Requires-Dist: requests<3.0.0,>=2.31.0; extra == "all"
Requires-Dist: requests-oauthlib<2.0.0,>=1.3.0; extra == "all"
Requires-Dist: msal<2.0.0,>=1.24.0; extra == "all"
Requires-Dist: azure-identity<2.0.0,>=1.15.0; extra == "all"
Requires-Dist: azure-storage-blob<13.0.0,>=12.19.0; extra == "all"
Requires-Dist: aiohttp<4.0.0,>=3.8.0; extra == "all"
Requires-Dist: pytest>=7.0.0; extra == "all"
Requires-Dist: pytest-cov>=4.0.0; extra == "all"
Requires-Dist: pytest-mock>=3.10.0; extra == "all"
Requires-Dist: pytest-asyncio>=0.21.0; extra == "all"
Requires-Dist: httpx>=0.24.0; extra == "all"
Requires-Dist: black>=23.0.0; extra == "all"
Requires-Dist: isort>=5.12.0; extra == "all"
Requires-Dist: mypy>=1.0.0; extra == "all"
Requires-Dist: flake8>=6.0.0; extra == "all"
Requires-Dist: bandit>=1.7.0; extra == "all"
Requires-Dist: types-requests>=2.31.0; extra == "all"
Dynamic: license-file
